MANIFEST.in
OSMC-License.txt
README.md
build_helpers.py
pyproject.toml
OMSimulator.egg-info/PKG-INFO
OMSimulator.egg-info/SOURCES.txt
OMSimulator.egg-info/dependency_links.txt
OMSimulator.egg-info/not-zip-safe
OMSimulator.egg-info/requires.txt
OMSimulator.egg-info/top_level.txt