Metadata-Version: 2.4
Name: OMSimulator
Version: 3.0.0.post103
Summary: OMSimulator - the FMI-based co-simulation environment for Python
Author-email: "Open Source Modelica Consortium (OSMC)" <openmodelicadevelopers@ida.liu.se>
Project-URL: Homepage, http://openmodelica.org/
Project-URL: Documentation, https://openmodelica.org/doc/OMSimulator/master/OMSimulator/UsersGuide/html/
Project-URL: Source Code, https://github.com/OpenModelica/OMSimulator
Project-URL: Issues, https://github.com/OpenModelica/OMSimulator/issues
Project-URL: Release Notes, https://github.com/OpenModelica/OMSimulator/releases
Project-URL: Download, https://pypi.org/project/OMSimulator/#files
Requires-Python: >=3.10
License-File: OSMC-License.txt
Requires-Dist: requests
Requires-Dist: lxml>=5.3.1
Dynamic: license-file
